{
  "inputSpec": "./input/CustomContent.openapi.yaml",
  "outputDir": "classes/",
  "generatorName": "java",
  "templateDir": "templates/wrapper/",
  "globalProperties": {
    "models": "customContentWrapper",
    "apis": false,
    "apiTests": false,
    "apiDocs": false,
    "modelDocs": false,
    "modelTests": false
  },
  "additionalProperties": {
    "library": "native",
    "modelPackage": "com.hubsante.model.customcontent",
    "serializationLibrary": "jackson",
    "openApiNullable": true,
    "supportUrlQuery": false,
    "enablePostProcessFile": true
  }
}